upstream_api_client/__init__.py
upstream_api_client/api_client.py
upstream_api_client/api_response.py
upstream_api_client/configuration.py
upstream_api_client/exceptions.py
upstream_api_client/py.typed
upstream_api_client/rest.py
upstream_api_client/api/__init__.py
upstream_api_client/api/auth_api.py
upstream_api_client/api/campaigns_api.py
upstream_api_client/api/measurements_api.py
upstream_api_client/api/projects_api.py
upstream_api_client/api/sensor_variables_api.py
upstream_api_client/api/sensors_api.py
upstream_api_client/api/stations_api.py
upstream_api_client/api/uploadfile_csv_api.py
upstream_api_client/models/__init__.py
upstream_api_client/models/aggregated_measurement.py
upstream_api_client/models/bbox.py
upstream_api_client/models/campaign_create_response.py
upstream_api_client/models/campaign_update.py
upstream_api_client/models/campaigns_in.py
upstream_api_client/models/coordinates.py
upstream_api_client/models/force_update_sensor_statistics_response.py
upstream_api_client/models/geometry_collection.py
upstream_api_client/models/geometry_collection_geometries_inner.py
upstream_api_client/models/get_campaign_response.py
upstream_api_client/models/get_campaign_response_geometry.py
upstream_api_client/models/get_sensor_response.py
upstream_api_client/models/get_station_response.py
upstream_api_client/models/get_station_response_geometry.py
upstream_api_client/models/http_validation_error.py
upstream_api_client/models/line_string.py
upstream_api_client/models/line_string_coordinates_inner.py
upstream_api_client/models/list_campaigns_response_item.py
upstream_api_client/models/list_campaigns_response_item_geometry.py
upstream_api_client/models/list_campaigns_response_pagination.py
upstream_api_client/models/list_measurements_response_pagination.py
upstream_api_client/models/list_sensors_response_pagination.py
upstream_api_client/models/list_stations_response_pagination.py
upstream_api_client/models/location.py
upstream_api_client/models/login_response.py
upstream_api_client-0.1.9.dist-info/METADATA
upstream_api_client-0.1.9.dist-info/WHEEL
upstream_api_client-0.1.9.dist-info/top_level.txt
upstream_api_client-0.1.9.dist-info/RECORD
