Metadata-Version: 2.4
Name: upstream_api_client
Version: 0.1.9
Summary: Upstream Sensor Storage
Home-page: https://github.com/In-For-Disaster-Analytics/upstream-python-api-client
Author: Will Mobley
Author-email: Will Mobley <wmobley@tacc.utexas.edu>
License-Expression: MIT
Project-URL: Repository, https://github.com/In-For-Disaster-Analytics/upstream-python-api-client
Keywords: OpenAPI,OpenAPI-Generator,Upstream Sensor Storage
Requires-Python: >=3.9
Requires-Dist: urllib3<3.0.0,>=2.1.0
Requires-Dist: python-dateutil>=2.8.2
Requires-Dist: pydantic>=2
Requires-Dist: typing-extensions>=4.7.1
Dynamic: author
Dynamic: home-page
